{
    "description": "plate 7x1x3",
    "id": "oobe_plate_07_01_03",
    "type": "plate",
    "width": 7,
    "height": 1,
    "thickness": 3,
    "width_mm": 104,
    "thickness_mm": 3,
    "height_mm": 14,
    "components": [
        {
            "type": "p",
            "shape": "rounded_rectangle",
            "size": [
                52.0,
                7.0,
                3
            ],
            "r": 2.5,
            "pos": [
                0,
                0,
                0
            ],
            "height": 1,
            "width": 7,
            "m": ""
        },
        {
            "type": "negative",
            "shape": "hole",
            "r": 1.5,
            "pos": [
                -22.5,
                0.0,
                0
            ],
            "inclusion": "laser"
        },
        {
            "type": "negative",
            "shape": "hole",
            "r": 1.5,
            "pos": [
                -15.0,
                0.0,
                0
            ],
            "inclusion": "laser"
        },
        {
            "type": "negative",
            "shape": "hole",
            "r": 1.5,
            "pos": [
                -7.5,
                0.0,
                0
            ],
            "inclusion": "laser"
        },
        {
            "type": "negative",
            "shape": "hole",
            "r": 1.5,
            "pos": [
                0.0,
                0.0,
                0
            ],
            "inclusion": "laser"
        },
        {
            "type": "negative",
            "shape": "hole",
            "r": 1.5,
            "pos": [
                7.5,
                0.0,
                0
            ],
            "inclusion": "laser"
        },
        {
            "type": "negative",
            "shape": "hole",
            "r": 1.5,
            "pos": [
                15.0,
                0.0,
                0
            ],
            "inclusion": "laser"
        },
        {
            "type": "negative",
            "shape": "hole",
            "r": 1.5,
            "pos": [
                22.5,
                0.0,
                0
            ],
            "inclusion": "laser"
        },
        {
            "type": "negative",
            "shape": "hole",
            "r": 1.8,
            "pos": [
                -22.5,
                0.0,
                0
            ],
            "inclusion": "3dpr"
        },
        {
            "type": "negative",
            "shape": "hole",
            "r": 1.8,
            "pos": [
                -15.0,
                0.0,
                0
            ],
            "inclusion": "3dpr"
        },
        {
            "type": "negative",
            "shape": "hole",
            "r": 1.8,
            "pos": [
                -7.5,
                0.0,
                0
            ],
            "inclusion": "3dpr"
        },
        {
            "type": "negative",
            "shape": "hole",
            "r": 1.8,
            "pos": [
                0.0,
                0.0,
                0
            ],
            "inclusion": "3dpr"
        },
        {
            "type": "negative",
            "shape": "hole",
            "r": 1.8,
            "pos": [
                7.5,
                0.0,
                0
            ],
            "inclusion": "3dpr"
        },
        {
            "type": "negative",
            "shape": "hole",
            "r": 1.8,
            "pos": [
                15.0,
                0.0,
                0
            ],
            "inclusion": "3dpr"
        },
        {
            "type": "negative",
            "shape": "hole",
            "r": 1.8,
            "pos": [
                22.5,
                0.0,
                0
            ],
            "inclusion": "3dpr"
        },
        {
            "type": "negative",
            "shape": "hole",
            "r": 1.5,
            "pos": [
                -22.5,
                0.0,
                0
            ],
            "inclusion": "true"
        },
        {
            "type": "negative",
            "shape": "hole",
            "r": 1.5,
            "pos": [
                -15.0,
                0.0,
                0
            ],
            "inclusion": "true"
        },
        {
            "type": "negative",
            "shape": "hole",
            "r": 1.5,
            "pos": [
                -7.5,
                0.0,
                0
            ],
            "inclusion": "true"
        },
        {
            "type": "negative",
            "shape": "hole",
            "r": 1.5,
            "pos": [
                0.0,
                0.0,
                0
            ],
            "inclusion": "true"
        },
        {
            "type": "negative",
            "shape": "hole",
            "r": 1.5,
            "pos": [
                7.5,
                0.0,
                0
            ],
            "inclusion": "true"
        },
        {
            "type": "negative",
            "shape": "hole",
            "r": 1.5,
            "pos": [
                15.0,
                0.0,
                0
            ],
            "inclusion": "true"
        },
        {
            "type": "negative",
            "shape": "hole",
            "r": 1.5,
            "pos": [
                22.5,
                0.0,
                0
            ],
            "inclusion": "true"
        }
    ]
}